{
  "actor_id": "human://v9-4/user",
  "actor_type": "human_user",
  "audit_ref": "audit://v9-4/coding-workflow/coding-run-v9-4-cc92a93489f2",
  "auto_commit_performed": false,
  "auto_deploy_performed": false,
  "auto_push_performed": false,
  "coding_workflow_run_id": "coding-run-v9-4-cc92a93489f2",
  "correlation_id": "corr-v9-4-d86949a421",
  "created_at": "2026-06-10T06:30:28Z",
  "diff_proposal_ref": "diff-proposal-ref://v9-4/bounded-coding-workflow",
  "fix_loop_ref": "fix-loop-ref://v9-4/bounded-coding-workflow",
  "goal_ref": "goal-ref://v9-4/bounded-coding-workflow",
  "high_risk_decision_ref": "v9-4-autonomous-coding-workflow-pilot-approved",
  "human_authorization_ref": "human-auth://v9-4/autonomous-coding-workflow-pilot",
  "human_review_handoff_ref": "handoff-v9-4-8e30cd2e575a",
  "intent_ref": "intent-ref://v9-4/bounded-coding-workflow",
  "patch_applied": false,
  "plan_ref": "plan-ref://v9-4/bounded-coding-workflow",
  "proposal_only": true,
  "request_id": "req-v9-4-a064526375",
  "review_summary_is_approval": false,
  "review_summary_ref": "review-summary-ref://v9-4/bounded-coding-workflow",
  "schema_version": "v9_4.coding_workflow_run.v1",
  "source": "product_console",
  "source_agent_direct_mutation_denied": true,
  "spec_ref": "spec-ref://v9-4/bounded-coding-workflow",
  "test_plan_ref": "test-plan-ref://v9-4/bounded-coding-workflow",
  "test_result_ref": "test-result-ref://v9-4/7718e15446d0",
  "workspace_scope_ref": "workspace-ref://v9-4/harnessOS"
}
